[{"children":[{"dateAdded":1628827520502,"id":"5","index":0,"parentId":"1","title":"百度","url":"https://www.baidu.com/"},{"children":[{"dateAdded":1640170965160,"id":"54","index":0,"parentId":"7","title":"热门电视剧","url":"https://movie.douban.com/tv/#!type=tv&tag=%E7%83%AD%E9%97%A8&sort=recommend&page_limit=20&page_start=20"},{"dateAdded":1628834694921,"id":"6","index":1,"parentId":"7","title":"哔哩哔哩 (゜-゜)つロ 干杯~-bilibili","url":"https://www.bilibili.com/"},{"dateAdded":1633166301075,"id":"27","index":2,"parentId":"7","title":"《神探夏洛克 第四季》全集/Sherlock Season 4在线观看 | 91美剧网","url":"https://91mjw.com/video/1469.htm"},{"dateAdded":1633783300470,"id":"31","index":3,"parentId":"7","title":"西瓜视频 - 高清免费在线视频 - 点亮对生活的好奇心","url":"https://www.ixigua.com/"},{"dateAdded":1634569744121,"id":"33","index":4,"parentId":"7","title":"最新动画片 - 被窝电影","url":"http://www.kmpos.net/vodtype/4.html"},{"dateAdded":1635866495778,"id":"40","index":5,"parentId":"7","title":"2020最新热门电视剧，经典电视剧，电视剧 第1页-骑士影院","url":"https://www.74yyz.com/74yy/2.html"},{"dateAdded":1637420698769,"id":"46","index":6,"parentId":"7","title":"嗜血法医搜索结果 - 人人美剧","url":"https://www.rrmeiju.com/vodsearch/-------------.html"},{"dateAdded":1639060877755,"id":"48","index":7,"parentId":"7","title":"电视剧大全-电视剧排行榜 - 38影院","url":"http://www.38yy.cn/tv_rankpoint_104____1_1.html"},{"dateAdded":1639667719655,"id":"50","index":8,"parentId":"7","title":"电视剧 - 电影天堂","url":"https://www.dy2818.com/vodtype/2.html"},{"dateAdded":1639828133556,"id":"52","index":9,"parentId":"7","title":"电视剧频道第1页-热门好看的电视剧免费在线观看-策驰影院","url":"http://www.ynzdhc.com/cc_type/bb.html"},{"dateAdded":1645513287908,"id":"56","index":10,"parentId":"7","title":"电视剧频道_放放电影网","url":"http://www.ffytv.com/type/2-1.html"},{"dateAdded":1646374906573,"id":"63","index":11,"parentId":"7","title":"《龙门镖局》第1集在线观看－电视剧－星辰影院","url":"http://www.5zcake.com/dianshiju/longmenbiaoju/6-1"},{"dateAdded":1646393911813,"id":"65","index":12,"parentId":"7","title":"龙门镖局完整版免费全集百度云在线观看-国产剧-4m影院","url":"https://www.doudouso.com/v/2208.html"},{"dateAdded":1647684237942,"id":"67","index":13,"parentId":"7","title":"动画片bt种子下载 | CK电影部落","url":"https://www.ck180.net/arts/"},{"dateAdded":1647929459338,"id":"69","index":14,"parentId":"7","title":"2021最新好看的免费国产电视剧推荐_热门免费观看国产电视剧大全排行榜_第1页-樱花动漫影视电视剧","url":"http://www.tshongrui.com/index/13.html"}],"dateAdded":1628834706641,"dateGroupModified":1648110777131,"id":"7","index":1,"parentId":"1","title":"movie"},{"children":[{"dateAdded":1629094252378,"id":"15","index":0,"parentId":"13","title":"阴阳师 NGA玩家社区","url":"https://bbs.nga.cn/thread.php?fid=538&rand=686"}],"dateAdded":1628927978886,"dateGroupModified":1633783300470,"id":"13","index":2,"parentId":"1","title":"game"},{"children":[{"dateAdded":1631105609377,"id":"23","index":0,"parentId":"22","title":"磁力链接搜索-磁力搜索引擎神器大全-bt磁力天堂在线","url":"http://www.eryi.org/searchsites/cili-search.html"},{"dateAdded":1649856303835,"id":"89","index":1,"parentId":"22","title":"宅男俱乐部 | 番号社，日本女优，经典番号，欧美女优","url":"https://www.kamnice.com/"}],"dateAdded":1631105605578,"dateGroupModified":1650265301181,"id":"22","index":3,"parentId":"1","title":"other"},{"children":[{"dateAdded":1648537157477,"id":"79","index":0,"parentId":"58","title":"网易邮箱6.0版","url":"https://mail.163.com/"},{"dateAdded":1650880440828,"id":"101","index":1,"parentId":"58","title":"QQ邮箱 - 收件箱","url":"https://mail.qq.com/cgi-bin/frame_html?sid=_PSB7BB_h-OVYytJ&r=c571359c950218ec0623ebecf9f76a80"},{"dateAdded":1650294182950,"id":"94","index":2,"parentId":"58","title":"我的简历_猎聘","url":"https://c.liepin.com/resume/getdefaultresume?templateId=&fromPage=resumeTemplate"},{"dateAdded":1645684562064,"id":"61","index":3,"parentId":"58","title":"【深圳招聘，求职】-前程无忧","url":"https://search.51job.com/list/040000,000000,0000,00,9,07,%2B,2,1.html?lang=c&postchannel=0000&workyear=99&cotype=99&degreefrom=99&jobterm=99&companysize=99&ord_field=0&dibiaoid=0&line=&welfare="},{"dateAdded":1650982561355,"id":"103","index":4,"parentId":"58","title":"GitHub中文社区","url":"https://www.githubs.cn/"},{"dateAdded":1650984441965,"id":"105","index":5,"parentId":"58","title":"GitHub","url":"https://github.com/"}],"dateAdded":1645600855827,"dateGroupModified":1650984441965,"id":"58","index":4,"parentId":"1","title":"work"},{"children":[{"dateAdded":1650800890394,"id":"98","index":0,"parentId":"99","title":"Spring Boot starter入门","url":"http://c.biancheng.net/spring_boot/starter.html"},{"dateAdded":1648612286971,"id":"81","index":1,"parentId":"99","title":"主页 | JavaGuide","url":"https://javaguide.cn/"},{"dateAdded":1650265301181,"id":"91","index":2,"parentId":"99","title":"Java面试宝典（超级详细）_Jason贺_IT的博客-CSDN博客_java面试宝典","url":"https://blog.csdn.net/weixin_44165106/article/details/115572319"},{"dateAdded":1649131010575,"id":"85","index":3,"parentId":"99","title":"Java 正则表达式 | 菜鸟教程","url":"https://www.runoob.com/java/java-regular-expressions.html"},{"dateAdded":1650696352289,"id":"96","index":4,"parentId":"99","title":"行业消息-SpringForAll社区","url":"http://spring4all.com/internet-news"},{"dateAdded":1650272709301,"id":"92","index":5,"parentId":"99","title":"十个经典java开发项目及其描述-马上写到你的简历中去吧，祝你升职加薪_福建沙县小吃的博客-CSDN博客_java项目描述","url":"https://blog.csdn.net/weixin_40517799/article/details/117592739"},{"dateAdded":1648440418877,"id":"74","index":6,"parentId":"99","title":"Java博客-专业IT技术发表平台","url":"https://blog.csdn.net/nav/java"},{"dateAdded":1648785860255,"id":"83","index":7,"parentId":"99","title":"《Java 7程序设计入门经典》一2.2　Java的基本数据类型-阿里云开发者社区","url":"https://developer.aliyun.com/article/175601?spm=a2c6h.13813017.content3.1.7c436607xkzkFU"},{"dateAdded":1648440382592,"id":"73","index":8,"parentId":"99","title":"Java基础","url":"https://snailclimb.gitee.io/javaguide-interview/#/./docs/b-1%E9%9D%A2%E8%AF%95%E9%A2%98%E6%80%BB%E7%BB%93-Java%E5%9F%BA%E7%A1%80"},{"dateAdded":1648532118903,"id":"76","index":9,"parentId":"99","title":"华为机试题库_在线编程+题解_牛客题霸_牛客网","url":"https://www.nowcoder.com/ta/huawei"},{"dateAdded":1649411706785,"id":"87","index":10,"parentId":"99","title":"题库 - 力扣 (LeetCode) 全球极客挚爱的技术成长平台","url":"https://leetcode-cn.com/problemset/all/"}],"dateAdded":1650800905779,"dateGroupModified":1650880440828,"id":"99","index":5,"parentId":"1","title":"student"}],"dateAdded":1628827488389,"dateGroupModified":1631105609377,"id":"1","index":0,"parentId":"0","title":"书签栏"}]